tapr/__init__.py
tapr/io_/__init__.py
tapr/io_/ntableio.py
tapr/io_/serialization.py
tapr/main/__init__.py
tapr/main/alchemy.py
tapr/main/conversion.py
tapr/main/defs.py
tapr/main/engines.py
tapr/main/filtering.py
tapr/main/handling.py
tapr/main/ntable.py
tapr/main/processing.py
tapr/main/qol.py
tapr/main/structure.py
tapr/main/tabularization.py
tapr/main/ttypes.py
tapr/main/utils.py
tapr/visualization/__init__.py
tapr/visualization/matplotlib/__init__.py
tapr/visualization/matplotlib/pyplot.py
tapr/visualization/plotly/__init__.py
tapr/visualization/plotly/express.py
tapr/visualization/plotly/graph_objs.py
tapr/visualization/plotly/offline.py
tapr/visualization/plotly/subplots.py
tapr-0.3.1.dist-info/LICENSE
tapr-0.3.1.dist-info/METADATA
tapr-0.3.1.dist-info/WHEEL
tapr-0.3.1.dist-info/top_level.txt
tapr-0.3.1.dist-info/RECORD
