Metadata-Version: 2.1
Name: tapr
Version: 0.3.1
Summary: TAbular PRogramming in Python
Author-email: thecodedog <elcodedog@gmail.com>
Project-URL: Homepage, https://github.com/thecodedog/tapr
Project-URL: Bug Tracker, https://github.com/thecodedog/tapr/issues
Classifier: Programming Language :: Python :: 3
Classifier: License :: OSI Approved :: MIT License
Classifier: Operating System :: OS Independent
Requires-Python: >=3.10
License-File: LICENSE
Requires-Dist: h5py (==3.8.0)
Requires-Dist: numpy (==1.24.3)
Requires-Dist: pandas (==2.0.1)
Requires-Dist: plotly (==5.14.1)
Requires-Dist: xarray (==2023.4.2)
